spotter/__init__.py
spotter/core.py
spotter/distributions.py
spotter/doppler.py
spotter/kernels.py
spotter/light_curves.py
spotter/star.py
spotter/utils.py
spotter/viz.py
starspotter-0.0.1.dist-info/METADATA
starspotter-0.0.1.dist-info/WHEEL
starspotter-0.0.1.dist-info/licenses/LICENSE
starspotter-0.0.1.dist-info/RECORD
