Metadata-Version: 2.3
Name: starspotter
Version: 0.0.1
Summary: Stellar contamination estimates from rotational light curves
Author: Lionel Garcia, Benjamin Rackham
License-Expression: MIT
License-File: LICENSE
Requires-Python: >=3.9
Requires-Dist: equinox
Requires-Dist: healpy
Requires-Dist: jax
Requires-Dist: jaxlib
Requires-Dist: numpy
Requires-Dist: tinygp
Provides-Extra: compare-starry
Requires-Dist: exoplanet-core; extra == 'compare-starry'
Requires-Dist: numpy<1.22; extra == 'compare-starry'
Requires-Dist: starry; extra == 'compare-starry'
Requires-Dist: tqdm; extra == 'compare-starry'
Requires-Dist: xarray<2023.10.0; extra == 'compare-starry'
Provides-Extra: comparison
Requires-Dist: jaxoplanet; extra == 'comparison'
Provides-Extra: dev
Requires-Dist: black; extra == 'dev'
Requires-Dist: nox; extra == 'dev'
Requires-Dist: pytest; extra == 'dev'
Provides-Extra: docs
Requires-Dist: docutils; extra == 'docs'
Requires-Dist: ipywidgets; extra == 'docs'
Requires-Dist: jupyterlab; extra == 'docs'
Requires-Dist: matplotlib; extra == 'docs'
Requires-Dist: myst-nb; extra == 'docs'
Requires-Dist: myst-parser; extra == 'docs'
Requires-Dist: sphinx; extra == 'docs'
Requires-Dist: sphinx-autoapi<3.2.0; extra == 'docs'
Requires-Dist: sphinx-book-theme; extra == 'docs'
Requires-Dist: sphinx-copybutton; extra == 'docs'
Requires-Dist: toml; extra == 'docs'
Provides-Extra: test
Requires-Dist: pytest; extra == 'test'
Requires-Dist: pytest-xdist; extra == 'test'
